accelerated_numpy/ACCELERATED_NUMPY.h
accelerated_numpy/__init__.py
accelerated_numpy/_accelerated_numpy.abi3.so
accelerated_numpy/_accelerated_numpy.cpp
accelerated_numpy/common.h
accelerated_numpy/ledger.cpp
accelerated_numpy/module_init.cpp
accelerated_numpy/recycler.cpp
accelerated_numpy/stubs.h
accelerated_numpy/tests/__init__.py
accelerated_numpy-0.1.0.dist-info/AUTHORS.rst
accelerated_numpy-0.1.0.dist-info/LICENSE
accelerated_numpy-0.1.0.dist-info/METADATA
accelerated_numpy-0.1.0.dist-info/WHEEL
accelerated_numpy-0.1.0.dist-info/top_level.txt
accelerated_numpy-0.1.0.dist-info/RECORD
