Metadata-Version: 2.1
Name: accelerated-numpy
Version: 0.1.0
Summary: Faster loops for NumPy using multithreading and other tricks
Home-page: https://github.com/Quansight/numpy-threading-extensions
Author: Matti Picus
Author-email: mattigit@picus.org.il
License: MIT
Project-URL: Changelog, https://github.com/Quansight/numpy-threading-extensions/blob/master/CHANGELOG.rst
Project-URL: Issue Tracker, https://github.com/Quansight/numpy-threading-extensions/issues
Platform: UNKNOWN
Classifier: Development Status :: 4 - Beta
Classifier: Intended Audience :: Developers
Classifier: License :: OSI Approved :: MIT License
Classifier: Operating System :: Unix
Classifier: Operating System :: POSIX
Classifier: Operating System :: Microsoft :: Windows
Classifier: Programming Language :: Python
Classifier: Programming Language :: Python :: 3
Classifier: Programming Language :: Python :: 3.6
Classifier: Programming Language :: Python :: 3.7
Classifier: Programming Language :: Python :: 3.8
Classifier: Programming Language :: Python :: Implementation :: CPython
Classifier: Programming Language :: Python :: Implementation :: PyPy
Classifier: Topic :: Utilities
Requires-Python: >=3.6
Requires-Dist: numpy (>=1.19.0)
